{"analysis":{"average_outcomes_per_draw":20.0,"bingo_total_test":null,"digits":[{"count":4413,"digit":0,"rate":0.099526},{"count":4488,"digit":1,"rate":0.101218},{"count":4483,"digit":2,"rate":0.101105},{"count":4419,"digit":3,"rate":0.099662},{"count":4310,"digit":4,"rate":0.097203},{"count":4526,"digit":5,"rate":0.102075},{"count":4612,"digit":6,"rate":0.104014},{"count":4332,"digit":7,"rate":0.0977},{"count":4379,"digit":8,"rate":0.09876},{"count":4378,"digit":9,"rate":0.098737}],"draws":739,"months":[{"month":1,"outcomes":1280,"values":[{"count":416,"digit":0,"rate_per_position":0.108333},{"count":374,"digit":1,"rate_per_position":0.097396},{"count":378,"digit":2,"rate_per_position":0.098437},{"count":383,"digit":3,"rate_per_position":0.09974},{"count":378,"digit":4,"rate_per_position":0.098437},{"count":383,"digit":5,"rate_per_position":0.09974},{"count":414,"digit":6,"rate_per_position":0.107813},{"count":398,"digit":7,"rate_per_position":0.103646},{"count":358,"digit":8,"rate_per_position":0.093229},{"count":358,"digit":9,"rate_per_position":0.093229}]},{"month":2,"outcomes":1160,"values":[{"count":344,"digit":0,"rate_per_position":0.098851},{"count":363,"digit":1,"rate_per_position":0.10431},{"count":351,"digit":2,"rate_per_position":0.100862},{"count":328,"digit":3,"rate_per_position":0.094253},{"count":345,"digit":4,"rate_per_position":0.099138},{"count":365,"digit":5,"rate_per_position":0.104885},{"count":337,"digit":6,"rate_per_position":0.096839},{"count":325,"digit":7,"rate_per_position":0.093391},{"count":353,"digit":8,"rate_per_position":0.101437},{"count":369,"digit":9,"rate_per_position":0.106034}]},{"month":3,"outcomes":1320,"values":[{"count":348,"digit":0,"rate_per_position":0.087879},{"count":382,"digit":1,"rate_per_position":0.096465},{"count":397,"digit":2,"rate_per_position":0.100253},{"count":377,"digit":3,"rate_per_position":0.095202},{"count":361,"digit":4,"rate_per_position":0.091162},{"count":418,"digit":5,"rate_per_position":0.105556},{"count":449,"digit":6,"rate_per_position":0.113384},{"count":404,"digit":7,"rate_per_position":0.10202},{"count":401,"digit":8,"rate_per_position":0.101263},{"count":423,"digit":9,"rate_per_position":0.106818}]},{"month":4,"outcomes":1300,"values":[{"count":390,"digit":0,"rate_per_position":0.1},{"count":397,"digit":1,"rate_per_position":0.101795},{"count":423,"digit":2,"rate_per_position":0.108462},{"count":396,"digit":3,"rate_per_position":0.101538},{"count":374,"digit":4,"rate_per_position":0.095897},{"count":393,"digit":5,"rate_per_position":0.100769},{"count":377,"digit":6,"rate_per_position":0.096667},{"count":362,"digit":7,"rate_per_position":0.092821},{"count":417,"digit":8,"rate_per_position":0.106923},{"count":371,"digit":9,"rate_per_position":0.095128}]},{"month":5,"outcomes":1320,"values":[{"count":423,"digit":0,"rate_per_position":0.106818},{"count":375,"digit":1,"rate_per_position":0.094697},{"count":400,"digit":2,"rate_per_position":0.10101},{"count":437,"digit":3,"rate_per_position":0.110354},{"count":392,"digit":4,"rate_per_position":0.09899},{"count":402,"digit":5,"rate_per_position":0.101515},{"count":399,"digit":6,"rate_per_position":0.100758},{"count":386,"digit":7,"rate_per_position":0.097475},{"count":363,"digit":8,"rate_per_position":0.091667},{"count":383,"digit":9,"rate_per_position":0.096717}]},{"month":6,"outcomes":1140,"values":[{"count":321,"digit":0,"rate_per_position":0.09386},{"count":374,"digit":1,"rate_per_position":0.109357},{"count":361,"digit":2,"rate_per_position":0.105556},{"count":320,"digit":3,"rate_per_position":0.093567},{"count":322,"digit":4,"rate_per_position":0.094152},{"count":359,"digit":5,"rate_per_position":0.104971},{"count":357,"digit":6,"rate_per_position":0.104386},{"count":319,"digit":7,"rate_per_position":0.093275},{"count":347,"digit":8,"rate_per_position":0.101462},{"count":340,"digit":9,"rate_per_position":0.099415}]},{"month":7,"outcomes":1060,"values":[{"count":321,"digit":0,"rate_per_position":0.100943},{"count":328,"digit":1,"rate_per_position":0.103145},{"count":311,"digit":2,"rate_per_position":0.097799},{"count":290,"digit":3,"rate_per_position":0.091195},{"count":319,"digit":4,"rate_per_position":0.100314},{"count":343,"digit":5,"rate_per_position":0.107862},{"count":320,"digit":6,"rate_per_position":0.100629},{"count":309,"digit":7,"rate_per_position":0.09717},{"count":302,"digit":8,"rate_per_position":0.094969},{"count":337,"digit":9,"rate_per_position":0.105975}]},{"month":8,"outcomes":1080,"values":[{"count":346,"digit":0,"rate_per_position":0.10679},{"count":325,"digit":1,"rate_per_position":0.100309},{"count":318,"digit":2,"rate_per_position":0.098148},{"count":362,"digit":3,"rate_per_position":0.111728},{"count":322,"digit":4,"rate_per_position":0.099383},{"count":351,"digit":5,"rate_per_position":0.108333},{"count":324,"digit":6,"rate_per_position":0.1},{"count":303,"digit":7,"rate_per_position":0.093519},{"count":297,"digit":8,"rate_per_position":0.091667},{"count":292,"digit":9,"rate_per_position":0.090123}]},{"month":9,"outcomes":1180,"values":[{"count":372,"digit":0,"rate_per_position":0.105085},{"count":326,"digit":1,"rate_per_position":0.09209},{"count":350,"digit":2,"rate_per_position":0.09887},{"count":366,"digit":3,"rate_per_position":0.10339},{"count":365,"digit":4,"rate_per_position":0.103107},{"count":343,"digit":5,"rate_per_position":0.096893},{"count":382,"digit":6,"rate_per_position":0.10791},{"count":329,"digit":7,"rate_per_position":0.092938},{"count":349,"digit":8,"rate_per_position":0.098588},{"count":358,"digit":9,"rate_per_position":0.10113}]},{"month":10,"outcomes":1320,"values":[{"count":399,"digit":0,"rate_per_position":0.100758},{"count":401,"digit":1,"rate_per_position":0.101263},{"count":424,"digit":2,"rate_per_position":0.107071},{"count":353,"digit":3,"rate_per_position":0.089141},{"count":394,"digit":4,"rate_per_position":0.099495},{"count":372,"digit":5,"rate_per_position":0.093939},{"count":415,"digit":6,"rate_per_position":0.104798},{"count":400,"digit":7,"rate_per_position":0.10101},{"count":402,"digit":8,"rate_per_position":0.101515},{"count":400,"digit":9,"rate_per_position":0.10101}]},{"month":11,"outcomes":1300,"values":[{"count":357,"digit":0,"rate_per_position":0.091538},{"count":427,"digit":1,"rate_per_position":0.109487},{"count":377,"digit":2,"rate_per_position":0.096667},{"count":384,"digit":3,"rate_per_position":0.098462},{"count":375,"digit":4,"rate_per_position":0.096154},{"count":387,"digit":5,"rate_per_position":0.099231},{"count":410,"digit":6,"rate_per_position":0.105128},{"count":400,"digit":7,"rate_per_position":0.102564},{"count":397,"digit":8,"rate_per_position":0.101795},{"count":386,"digit":9,"rate_per_position":0.098974}]},{"month":12,"outcomes":1320,"values":[{"count":376,"digit":0,"rate_per_position":0.094949},{"count":416,"digit":1,"rate_per_position":0.105051},{"count":393,"digit":2,"rate_per_position":0.099242},{"count":423,"digit":3,"rate_per_position":0.106818},{"count":363,"digit":4,"rate_per_position":0.091667},{"count":410,"digit":5,"rate_per_position":0.103535},{"count":428,"digit":6,"rate_per_position":0.108081},{"count":397,"digit":7,"rate_per_position":0.100253},{"count":393,"digit":8,"rate_per_position":0.099242},{"count":361,"digit":9,"rate_per_position":0.091162}]}],"most_frequent_sequences":[{"count":27,"sequence":"605"},{"count":27,"sequence":"746"},{"count":26,"sequence":"769"},{"count":25,"sequence":"159"},{"count":25,"sequence":"896"},{"count":24,"sequence":"420"},{"count":24,"sequence":"217"},{"count":24,"sequence":"542"},{"count":24,"sequence":"480"},{"count":24,"sequence":"089"},{"count":23,"sequence":"190"},{"count":23,"sequence":"623"},{"count":23,"sequence":"598"},{"count":23,"sequence":"624"},{"count":23,"sequence":"207"},{"count":23,"sequence":"555"},{"count":23,"sequence":"008"},{"count":22,"sequence":"087"},{"count":22,"sequence":"262"},{"count":22,"sequence":"809"}],"outcomes":14780,"positions":[{"normalized_entropy":0.99970689,"position":1,"values":[{"count":1500,"digit":0,"rate":0.101488},{"count":1548,"digit":1,"rate":0.104736},{"count":1493,"digit":2,"rate":0.101015},{"count":1522,"digit":3,"rate":0.102977},{"count":1444,"digit":4,"rate":0.0977},{"count":1493,"digit":5,"rate":0.101015},{"count":1446,"digit":6,"rate":0.097835},{"count":1515,"digit":7,"rate":0.102503},{"count":1474,"digit":8,"rate":0.099729},{"count":1345,"digit":9,"rate":0.091001}]},{"normalized_entropy":0.99969919,"position":2,"values":[{"count":1469,"digit":0,"rate":0.099391},{"count":1487,"digit":1,"rate":0.100609},{"count":1525,"digit":2,"rate":0.10318},{"count":1444,"digit":3,"rate":0.0977},{"count":1416,"digit":4,"rate":0.095805},{"count":1566,"digit":5,"rate":0.105954},{"count":1527,"digit":6,"rate":0.103315},{"count":1374,"digit":7,"rate":0.092963},{"count":1457,"digit":8,"rate":0.098579},{"count":1515,"digit":9,"rate":0.102503}]},{"normalized_entropy":0.99967936,"position":3,"values":[{"count":1444,"digit":0,"rate":0.0977},{"count":1453,"digit":1,"rate":0.098309},{"count":1465,"digit":2,"rate":0.09912},{"count":1453,"digit":3,"rate":0.098309},{"count":1450,"digit":4,"rate":0.098106},{"count":1467,"digit":5,"rate":0.099256},{"count":1639,"digit":6,"rate":0.110893},{"count":1443,"digit":7,"rate":0.097632},{"count":1448,"digit":8,"rate":0.09797},{"count":1518,"digit":9,"rate":0.102706}]}],"sequence_length":3,"sum_distribution":[{"count":12,"value":0},{"count":47,"value":1},{"count":77,"value":2},{"count":145,"value":3},{"count":222,"value":4},{"count":322,"value":5},{"count":391,"value":6},{"count":519,"value":7},{"count":687,"value":8},{"count":774,"value":9},{"count":964,"value":10},{"count":1092,"value":11},{"count":1097,"value":12},{"count":1107,"value":13},{"count":1124,"value":14},{"count":1086,"value":15},{"count":1005,"value":16},{"count":955,"value":17},{"count":787,"value":18},{"count":652,"value":19},{"count":495,"value":20},{"count":407,"value":21},{"count":316,"value":22},{"count":208,"value":23},{"count":154,"value":24},{"count":73,"value":25},{"count":44,"value":26},{"count":18,"value":27}],"uniformity":{"approximate_p_value":0.0398383,"chi_square":17.607578,"cohens_w":0.019927,"degrees_of_freedom":9,"normalized_entropy":0.99991404},"unique_digit_distribution":[{"count":153,"value":1},{"count":3853,"value":2},{"count":10774,"value":3}]},"audit":{"audit_interval_draws":100,"conclusion":"Có 2 kiểm định chỉ đạt một trong hai điều kiện thống kê hoặc độ lớn thực dụng. Cần đọc riêng lý do thay vì gộp thành một nhãn theo dõi.","dependency_families":[{"correction_scope":"number-set marginal counts, calendar strata and gap history","id":"number_frequency_history","label":"Tần suất số theo lịch sử","plain_language":"Các phép kiểm cùng đọc lịch sử xuất hiện của từng số, từ tổng tần suất đến tháng quay và khoảng vắng hiện tại.","test_ids":["number_current_gap_geometric","number_marginal_chi_square","number_marginal_g_test","number_month_heterogeneity"]},{"correction_scope":"draw-order sum statistics for number-set products","id":"number_ordered_summary","label":"Chuỗi tổng bộ số","plain_language":"Các phép kiểm dùng cùng chuỗi tổng của từng kỳ để đọc nhịp cao-thấp, tự tương quan và đổi chế độ theo thời gian.","test_ids":["number_sum_lag1_autocorrelation","number_sum_runs","number_sum_split_half_change"]},{"correction_scope":"within-draw combination structure for number-set products","id":"number_within_draw_structure","label":"Cấu trúc trong cùng kỳ","plain_language":"Các phép kiểm dùng đặc trưng sinh ra từ cùng một bộ số trong một kỳ, như cặp đồng xuất hiện hoặc số lượng số lẻ.","test_ids":["number_odd_count_hypergeometric","number_pair_co_occurrence"]},{"correction_scope":"digit counts, position counts and calendar strata","id":"digit_frequency_distribution","label":"Tần suất chữ số","plain_language":"Các phép kiểm cùng đọc số lần xuất hiện chữ số, có thể gộp toàn chuỗi, tách theo vị trí hoặc tách theo tháng.","test_ids":["digit_marginal_chi_square","digit_marginal_g_test","digit_month_heterogeneity","digit_position_chi_square"]},{"correction_scope":"draw-order value and digit-sum statistics","id":"digit_ordered_sequence","label":"Chuỗi kết quả theo thời gian","plain_language":"Các phép kiểm dùng thứ tự kỳ quay của chuỗi chữ số để đọc nhịp, tự tương quan hoặc đổi chế độ.","test_ids":["digit_sum_split_half_change","digit_value_lag1_autocorrelation","digit_value_runs"]},{"correction_scope":"within-outcome digit sums","id":"digit_sum_structure","label":"Tổng chữ số trong kết quả","plain_language":"Kiểm tra phân bố tổng chữ số của từng kết quả.","test_ids":["digit_sum_distribution"]},{"correction_scope":"duplicate outcome pairs","id":"digit_repeat_structure","label":"Lặp chuỗi kết quả","plain_language":"Kiểm tra số cặp kết quả trùng nhau trong không gian hữu hạn.","test_ids":["digit_repeat_poisson"]}],"dependency_matrix":{"counts":{"high":2,"low":27,"medium":7},"note":"Ma trận là bản đồ phụ thuộc phương pháp, không phải ma trận tương quan ước lượng từ dữ liệu. Cặp high thường dùng cùng dữ liệu và cùng câu hỏi; medium dùng chung họ phụ thuộc; low chỉ chia sẻ miền sản phẩm.","pair_count":36,"pairs":[{"dependency_strength":"high","left_id":"digit_marginal_chi_square","left_label":"Tần suất giá trị 0 đến 9","rationale":"Hai phép kiểm dùng cùng lát dữ liệu và trả lời gần như cùng một câu hỏi, nên không nên đọc như hai bằng chứng độc lập.","relationship":"same_question","right_id":"digit_marginal_g_test","right_label":"G-test cho tần suất giá trị","shared_tags":["digit_counts","digit_sequence","pooled_digits"]},{"dependency_strength":"medium","left_id":"digit_marginal_chi_square","left_label":"Tần suất giá trị 0 đến 9","rationale":"Hai phép kiểm dùng chung họ dữ liệu hoặc đặc trưng dẫn xuất, vì vậy kết quả có thể cùng phản ánh một sai lệch nền.","relationship":"same_dependency_family","right_id":"digit_month_heterogeneity","right_label":"Tần suất giá trị theo tháng","shared_tags":["digit_counts","digit_sequence"]},{"dependency_strength":"medium","left_id":"digit_marginal_chi_square","left_label":"Tần suất giá trị 0 đến 9","rationale":"Hai phép kiểm dùng chung họ dữ liệu hoặc đặc trưng dẫn xuất, vì vậy kết quả có thể cùng phản ánh một sai lệch nền.","relationship":"same_dependency_family","right_id":"digit_position_chi_square","right_label":"Tần suất giá trị theo vị trí","shared_tags":["digit_counts","digit_sequence"]},{"dependency_strength":"low","left_id":"digit_marginal_chi_square","left_label":"Tần suất giá trị 0 đến 9","rationale":"Hai phép kiểm cùng thuộc một miền sản phẩm nhưng nhìn các đặc trưng khác nhau.","relationship":"same_product_domain","right_id":"digit_repeat_poisson","right_label":"Tỷ lệ chuỗi lặp lại","shared_tags":["digit_sequence"]},{"dependency_strength":"low","left_id":"digit_marginal_chi_square","left_label":"Tần suất giá trị 0 đến 9","rationale":"Hai phép kiểm cùng thuộc một miền sản phẩm nhưng nhìn các đặc trưng khác nhau.","relationship":"same_product_domain","right_id":"digit_sum_distribution","right_label":"Phân bố tổng chữ số","shared_tags":["digit_sequence"]},{"dependency_strength":"low","left_id":"digit_marginal_chi_square","left_label":"Tần suất giá trị 0 đến 9","rationale":"Hai phép kiểm cùng thuộc một miền sản phẩm nhưng nhìn các đặc trưng khác nhau.","relationship":"same_product_domain","right_id":"digit_sum_split_half_change","right_label":"So nửa đầu và nửa sau bằng tổng chữ số","shared_tags":["digit_sequence"]},{"dependency_strength":"low","left_id":"digit_marginal_chi_square","left_label":"Tần suất giá trị 0 đến 9","rationale":"Hai phép kiểm cùng thuộc một miền sản phẩm nhưng nhìn các đặc trưng khác nhau.","relationship":"same_product_domain","right_id":"digit_value_lag1_autocorrelation","right_label":"Tự tương quan lag-1 của giá trị chuỗi","shared_tags":["digit_sequence"]},{"dependency_strength":"low","left_id":"digit_marginal_chi_square","left_label":"Tần suất giá trị 0 đến 9","rationale":"Hai phép kiểm cùng thuộc một miền sản phẩm nhưng nhìn các đặc trưng khác nhau.","relationship":"same_product_domain","right_id":"digit_value_runs","right_label":"Runs test trên giá trị chuỗi","shared_tags":["digit_sequence"]},{"dependency_strength":"medium","left_id":"digit_marginal_g_test","left_label":"G-test cho tần suất giá trị","rationale":"Hai phép kiểm dùng chung họ dữ liệu hoặc đặc trưng dẫn xuất, vì vậy kết quả có thể cùng phản ánh một sai lệch nền.","relationship":"same_dependency_family","right_id":"digit_month_heterogeneity","right_label":"Tần suất giá trị theo tháng","shared_tags":["digit_counts","digit_sequence"]},{"dependency_strength":"medium","left_id":"digit_marginal_g_test","left_label":"G-test cho tần suất giá trị","rationale":"Hai phép kiểm dùng chung họ dữ liệu hoặc đặc trưng dẫn xuất, vì vậy kết quả có thể cùng phản ánh một sai lệch nền.","relationship":"same_dependency_family","right_id":"digit_position_chi_square","right_label":"Tần suất giá trị theo vị trí","shared_tags":["digit_counts","digit_sequence"]},{"dependency_strength":"low","left_id":"digit_marginal_g_test","left_label":"G-test cho tần suất giá trị","rationale":"Hai phép kiểm cùng thuộc một miền sản phẩm nhưng nhìn các đặc trưng khác nhau.","relationship":"same_product_domain","right_id":"digit_repeat_poisson","right_label":"Tỷ lệ chuỗi lặp lại","shared_tags":["digit_sequence"]},{"dependency_strength":"low","left_id":"digit_marginal_g_test","left_label":"G-test cho tần suất giá trị","rationale":"Hai phép kiểm cùng thuộc một miền sản phẩm nhưng nhìn các đặc trưng khác nhau.","relationship":"same_product_domain","right_id":"digit_sum_distribution","right_label":"Phân bố tổng chữ số","shared_tags":["digit_sequence"]},{"dependency_strength":"low","left_id":"digit_marginal_g_test","left_label":"G-test cho tần suất giá trị","rationale":"Hai phép kiểm cùng thuộc một miền sản phẩm nhưng nhìn các đặc trưng khác nhau.","relationship":"same_product_domain","right_id":"digit_sum_split_half_change","right_label":"So nửa đầu và nửa sau bằng tổng chữ số","shared_tags":["digit_sequence"]},{"dependency_strength":"low","left_id":"digit_marginal_g_test","left_label":"G-test cho tần suất giá trị","rationale":"Hai phép kiểm cùng thuộc một miền sản phẩm nhưng nhìn các đặc trưng khác nhau.","relationship":"same_product_domain","right_id":"digit_value_lag1_autocorrelation","right_label":"Tự tương quan lag-1 của giá trị chuỗi","shared_tags":["digit_sequence"]},{"dependency_strength":"low","left_id":"digit_marginal_g_test","left_label":"G-test cho tần suất giá trị","rationale":"Hai phép kiểm cùng thuộc một miền sản phẩm nhưng nhìn các đặc trưng khác nhau.","relationship":"same_product_domain","right_id":"digit_value_runs","right_label":"Runs test trên giá trị chuỗi","shared_tags":["digit_sequence"]},{"dependency_strength":"medium","left_id":"digit_month_heterogeneity","left_label":"Tần suất giá trị theo tháng","rationale":"Hai phép kiểm dùng chung họ dữ liệu hoặc đặc trưng dẫn xuất, vì vậy kết quả có thể cùng phản ánh một sai lệch nền.","relationship":"same_dependency_family","right_id":"digit_position_chi_square","right_label":"Tần suất giá trị theo vị trí","shared_tags":["digit_counts","digit_sequence"]},{"dependency_strength":"low","left_id":"digit_month_heterogeneity","left_label":"Tần suất giá trị theo tháng","rationale":"Hai phép kiểm cùng thuộc một miền sản phẩm nhưng nhìn các đặc trưng khác nhau.","relationship":"same_product_domain","right_id":"digit_repeat_poisson","right_label":"Tỷ lệ chuỗi lặp lại","shared_tags":["digit_sequence"]},{"dependency_strength":"low","left_id":"digit_month_heterogeneity","left_label":"Tần suất giá trị theo tháng","rationale":"Hai phép kiểm cùng thuộc một miền sản phẩm nhưng nhìn các đặc trưng khác nhau.","relationship":"same_product_domain","right_id":"digit_sum_distribution","right_label":"Phân bố tổng chữ số","shared_tags":["digit_sequence"]},{"dependency_strength":"low","left_id":"digit_month_heterogeneity","left_label":"Tần suất giá trị theo tháng","rationale":"Hai phép kiểm cùng thuộc một miền sản phẩm nhưng nhìn các đặc trưng khác nhau.","relationship":"same_product_domain","right_id":"digit_sum_split_half_change","right_label":"So nửa đầu và nửa sau bằng tổng chữ số","shared_tags":["digit_sequence"]},{"dependency_strength":"low","left_id":"digit_month_heterogeneity","left_label":"Tần suất giá trị theo tháng","rationale":"Hai phép kiểm cùng thuộc một miền sản phẩm nhưng nhìn các đặc trưng khác nhau.","relationship":"same_product_domain","right_id":"digit_value_lag1_autocorrelation","right_label":"Tự tương quan lag-1 của giá trị chuỗi","shared_tags":["digit_sequence"]},{"dependency_strength":"low","left_id":"digit_month_heterogeneity","left_label":"Tần suất giá trị theo tháng","rationale":"Hai phép kiểm cùng thuộc một miền sản phẩm nhưng nhìn các đặc trưng khác nhau.","relationship":"same_product_domain","right_id":"digit_value_runs","right_label":"Runs test trên giá trị chuỗi","shared_tags":["digit_sequence"]},{"dependency_strength":"low","left_id":"digit_position_chi_square","left_label":"Tần suất giá trị theo vị trí","rationale":"Hai phép kiểm cùng thuộc một miền sản phẩm nhưng nhìn các đặc trưng khác nhau.","relationship":"same_product_domain","right_id":"digit_repeat_poisson","right_label":"Tỷ lệ chuỗi lặp lại","shared_tags":["digit_sequence"]},{"dependency_strength":"low","left_id":"digit_position_chi_square","left_label":"Tần suất giá trị theo vị trí","rationale":"Hai phép kiểm cùng thuộc một miền sản phẩm nhưng nhìn các đặc trưng khác nhau.","relationship":"same_product_domain","right_id":"digit_sum_distribution","right_label":"Phân bố tổng chữ số","shared_tags":["digit_sequence"]},{"dependency_strength":"low","left_id":"digit_position_chi_square","left_label":"Tần suất giá trị theo vị trí","rationale":"Hai phép kiểm cùng thuộc một miền sản phẩm nhưng nhìn các đặc trưng khác nhau.","relationship":"same_product_domain","right_id":"digit_sum_split_half_change","right_label":"So nửa đầu và nửa sau bằng tổng chữ số","shared_tags":["digit_sequence"]},{"dependency_strength":"low","left_id":"digit_position_chi_square","left_label":"Tần suất giá trị theo vị trí","rationale":"Hai phép kiểm cùng thuộc một miền sản phẩm nhưng nhìn các đặc trưng khác nhau.","relationship":"same_product_domain","right_id":"digit_value_lag1_autocorrelation","right_label":"Tự tương quan lag-1 của giá trị chuỗi","shared_tags":["digit_sequence"]},{"dependency_strength":"low","left_id":"digit_position_chi_square","left_label":"Tần suất giá trị theo vị trí","rationale":"Hai phép kiểm cùng thuộc một miền sản phẩm nhưng nhìn các đặc trưng khác nhau.","relationship":"same_product_domain","right_id":"digit_value_runs","right_label":"Runs test trên giá trị chuỗi","shared_tags":["digit_sequence"]},{"dependency_strength":"low","left_id":"digit_repeat_poisson","left_label":"Tỷ lệ chuỗi lặp lại","rationale":"Hai phép kiểm cùng thuộc một miền sản phẩm nhưng nhìn các đặc trưng khác nhau.","relationship":"same_product_domain","right_id":"digit_sum_distribution","right_label":"Phân bố tổng chữ số","shared_tags":["digit_sequence"]},{"dependency_strength":"low","left_id":"digit_repeat_poisson","left_label":"Tỷ lệ chuỗi lặp lại","rationale":"Hai phép kiểm cùng thuộc một miền sản phẩm nhưng nhìn các đặc trưng khác nhau.","relationship":"same_product_domain","right_id":"digit_sum_split_half_change","right_label":"So nửa đầu và nửa sau bằng tổng chữ số","shared_tags":["digit_sequence"]},{"dependency_strength":"low","left_id":"digit_repeat_poisson","left_label":"Tỷ lệ chuỗi lặp lại","rationale":"Hai phép kiểm cùng thuộc một miền sản phẩm nhưng nhìn các đặc trưng khác nhau.","relationship":"same_product_domain","right_id":"digit_value_lag1_autocorrelation","right_label":"Tự tương quan lag-1 của giá trị chuỗi","shared_tags":["digit_sequence"]},{"dependency_strength":"low","left_id":"digit_repeat_poisson","left_label":"Tỷ lệ chuỗi lặp lại","rationale":"Hai phép kiểm cùng thuộc một miền sản phẩm nhưng nhìn các đặc trưng khác nhau.","relationship":"same_product_domain","right_id":"digit_value_runs","right_label":"Runs test trên giá trị chuỗi","shared_tags":["digit_sequence"]},{"dependency_strength":"low","left_id":"digit_sum_distribution","left_label":"Phân bố tổng chữ số","rationale":"Hai phép kiểm cùng thuộc một miền sản phẩm nhưng nhìn các đặc trưng khác nhau.","relationship":"same_product_domain","right_id":"digit_sum_split_half_change","right_label":"So nửa đầu và nửa sau bằng tổng chữ số","shared_tags":["digit_sequence","digit_sum"]},{"dependency_strength":"low","left_id":"digit_sum_distribution","left_label":"Phân bố tổng chữ số","rationale":"Hai phép kiểm cùng thuộc một miền sản phẩm nhưng nhìn các đặc trưng khác nhau.","relationship":"same_product_domain","right_id":"digit_value_lag1_autocorrelation","right_label":"Tự tương quan lag-1 của giá trị chuỗi","shared_tags":["digit_sequence"]},{"dependency_strength":"low","left_id":"digit_sum_distribution","left_label":"Phân bố tổng chữ số","rationale":"Hai phép kiểm cùng thuộc một miền sản phẩm nhưng nhìn các đặc trưng khác nhau.","relationship":"same_product_domain","right_id":"digit_value_runs","right_label":"Runs test trên giá trị chuỗi","shared_tags":["digit_sequence"]},{"dependency_strength":"medium","left_id":"digit_sum_split_half_change","left_label":"So nửa đầu và nửa sau bằng tổng chữ số","rationale":"Hai phép kiểm dùng chung họ dữ liệu hoặc đặc trưng dẫn xuất, vì vậy kết quả có thể cùng phản ánh một sai lệch nền.","relationship":"same_dependency_family","right_id":"digit_value_lag1_autocorrelation","right_label":"Tự tương quan lag-1 của giá trị chuỗi","shared_tags":["digit_sequence","ordered_draws"]},{"dependency_strength":"medium","left_id":"digit_sum_split_half_change","left_label":"So nửa đầu và nửa sau bằng tổng chữ số","rationale":"Hai phép kiểm dùng chung họ dữ liệu hoặc đặc trưng dẫn xuất, vì vậy kết quả có thể cùng phản ánh một sai lệch nền.","relationship":"same_dependency_family","right_id":"digit_value_runs","right_label":"Runs test trên giá trị chuỗi","shared_tags":["digit_sequence","ordered_draws"]},{"dependency_strength":"high","left_id":"digit_value_lag1_autocorrelation","left_label":"Tự tương quan lag-1 của giá trị chuỗi","rationale":"Hai phép kiểm dùng cùng lát dữ liệu và trả lời gần như cùng một câu hỏi, nên không nên đọc như hai bằng chứng độc lập.","relationship":"same_question","right_id":"digit_value_runs","right_label":"Runs test trên giá trị chuỗi","shared_tags":["digit_sequence","numeric_value","ordered_draws"]}],"scope":"single_product","test_count":9},"effect_thresholds":[{"applies_to":["number_marginal_chi_square","digit_marginal_chi_square"],"effect_size_name":"Cohen's w","id":"cohen_w_0_05","reference_or_rationale":"Cohen thường xem w=0,10 là hiệu ứng nhỏ. Dự án dùng 0,05 như ngưỡng sàng lọc bảo thủ hơn vì sai lệch xổ số, nếu có, được kỳ vọng rất nhỏ và vẫn phải vượt hiệu chỉnh nhiều kiểm định.","scope":"Kiểm định phân bố biên cho tập số và chuỗi chữ số.","sensitivity_method":"Đếm lại số phép kiểm đạt ngưỡng khi nhân ngưỡng đã khóa với 0,5; 1,0; 1,5; 2,0.","threshold":0.05,"unit":"w = sqrt(chi_square / pooled category observations)"},{"applies_to":["number_marginal_g_test","digit_marginal_g_test"],"effect_size_name":"likelihood w","id":"likelihood_w_0_05","reference_or_rationale":"Dùng cùng mốc 0,05 với Cohen's w để hai phép kiểm cùng họ không tạo hai tiêu chuẩn thực dụng khác nhau cho cùng một sai lệch phân bố.","scope":"G-test cho cùng câu hỏi phân bố biên với chi-square.","sensitivity_method":"Đếm lại số phép kiểm đạt ngưỡng khi nhân ngưỡng đã khóa với 0,5; 1,0; 1,5; 2,0.","threshold":0.05,"unit":"w = sqrt(g_statistic / pooled category observations)"},{"applies_to":["number_sum_runs","digit_value_runs"],"effect_size_name":"absolute z per sqrt(n)","id":"absolute_z_per_sqrt_n_0_10","reference_or_rationale":"Chuẩn hóa z theo căn cỡ mẫu để mẫu rất lớn không tự biến sai lệch nhỏ thành tín hiệu thực dụng. Mốc 0,10 là mức tối thiểu trước khi coi nhịp cao-thấp là đủ lớn để theo dõi.","scope":"Runs test trên chuỗi tổng bộ số hoặc giá trị chuỗi.","sensitivity_method":"Đếm lại số phép kiểm đạt ngưỡng khi nhân ngưỡng đã khóa với 0,5; 1,0; 1,5; 2,0.","threshold":0.1,"unit":"|z| / sqrt(n)"},{"applies_to":["number_sum_lag1_autocorrelation","digit_value_lag1_autocorrelation"],"effect_size_name":"absolute correlation","id":"absolute_correlation_0_05","reference_or_rationale":"Tương quan 0,05 là hiệu ứng rất nhỏ theo thang r, nhưng vẫn đủ đáng chú ý trong bối cảnh xổ số nếu ổn định ngoài mẫu và vượt hiệu chỉnh.","scope":"Tự tương quan lag-1 của tổng bộ số hoặc giá trị chuỗi.","sensitivity_method":"Đếm lại số phép kiểm đạt ngưỡng khi nhân ngưỡng đã khóa với 0,5; 1,0; 1,5; 2,0.","threshold":0.05,"unit":"|r|"},{"applies_to":["number_sum_split_half_change","digit_sum_split_half_change"],"effect_size_name":"standardized mean difference","id":"standardized_mean_difference_0_15","reference_or_rationale":"Mốc này thấp hơn quy ước small-effect 0,20 của standardized mean difference để phục vụ cảnh báo sớm, nhưng vẫn buộc sai lệch phải lớn hơn nhiễu rất nhỏ của mẫu lớn.","scope":"So sánh split-half giữa nửa đầu và nửa sau lịch sử.","sensitivity_method":"Đếm lại số phép kiểm đạt ngưỡng khi nhân ngưỡng đã khóa với 0,5; 1,0; 1,5; 2,0.","threshold":0.15,"unit":"|mean_2 - mean_1| / pooled_sd"},{"applies_to":["number_month_heterogeneity","digit_month_heterogeneity"],"effect_size_name":"Cramer's style w","id":"cramers_style_w_0_05","reference_or_rationale":"Dùng cùng mốc sàng lọc 0,05 với các kiểm định chi-square phân bố, vì đây vẫn là độ lệch chuẩn hóa từ bảng phân loại nhưng có thêm tầng tháng.","scope":"Kiểm định dị biệt theo tháng cho số hoặc chữ số.","sensitivity_method":"Đếm lại số phép kiểm đạt ngưỡng khi nhân ngưỡng đã khóa với 0,5; 1,0; 1,5; 2,0.","threshold":0.05,"unit":"w = sqrt(chi_square / stratified observations)"},{"applies_to":["number_current_gap_geometric"],"effect_size_name":"gap divided by expected gap","id":"gap_ratio_4_0","reference_or_rationale":"Khoảng vắng phải đạt ít nhất bốn lần khoảng vắng kỳ vọng mới được xem là lớn về thực dụng, vì trong không gian nhiều số luôn có một số đang vắng lâu.","scope":"Số đang vắng lâu nhất trong sản phẩm chọn tập số.","sensitivity_method":"Đếm lại số phép kiểm đạt ngưỡng khi nhân ngưỡng đã khóa với 0,5; 1,0; 1,5; 2,0.","threshold":4.0,"unit":"current_gap_draws / expected_gap_draws"},{"applies_to":["number_pair_co_occurrence"],"effect_size_name":"pair co-occurrence w","id":"pair_co_occurrence_w_0_05","reference_or_rationale":"Giữ cùng mốc 0,05 với kiểm định phân bố, nhưng diễn giải thận trọng hơn vì các cặp trong cùng một kỳ không độc lập hoàn toàn.","scope":"Kiểm định đồng xuất hiện cặp số khi workflow đủ bộ nhớ để chạy.","sensitivity_method":"Đếm lại số phép kiểm đạt ngưỡng khi nhân ngưỡng đã khóa với 0,5; 1,0; 1,5; 2,0.","threshold":0.05,"unit":"w = sqrt(chi_square / pair observations)"},{"applies_to":["number_odd_count_hypergeometric"],"effect_size_name":"odd-count w","id":"odd_count_w_0_10","reference_or_rationale":"Số chẵn-lẻ là đặc trưng tổng hợp thô nên yêu cầu mốc 0,10, tránh báo tín hiệu thực dụng từ dao động nhỏ của vài ô phân bố.","scope":"Phân bố số lượng số lẻ trong một bộ chọn không lặp.","sensitivity_method":"Đếm lại số phép kiểm đạt ngưỡng khi nhân ngưỡng đã khóa với 0,5; 1,0; 1,5; 2,0.","threshold":0.1,"unit":"w = sqrt(chi_square / draws)"},{"applies_to":["digit_position_chi_square"],"effect_size_name":"position digit w","id":"position_digit_w_0_05","reference_or_rationale":"Đây là tín hiệu đang cần tái kiểm tra ngoài mẫu nên giữ ngưỡng nhạy 0,05, nhưng không tách từng ô thành kiểm định mới trên cùng dữ liệu.","scope":"Kiểm định chữ số theo vị trí cho Max 3D, Max 3D Pro, Max 4D và Bingo18.","sensitivity_method":"Đếm lại số phép kiểm đạt ngưỡng khi nhân ngưỡng đã khóa với 0,5; 1,0; 1,5; 2,0.","threshold":0.05,"unit":"w = sqrt(chi_square / position-digit observations)"},{"applies_to":["digit_sum_distribution"],"effect_size_name":"digit-sum w","id":"digit_sum_w_0_10","reference_or_rationale":"Tổng chữ số gộp nhiều cấu hình khác nhau, vì vậy dùng mốc 0,10 để chỉ đánh dấu sai lệch tổng hợp đủ lớn.","scope":"Phân bố tổng chữ số của sản phẩm chuỗi chữ số.","sensitivity_method":"Đếm lại số phép kiểm đạt ngưỡng khi nhân ngưỡng đã khóa với 0,5; 1,0; 1,5; 2,0.","threshold":0.1,"unit":"w = sqrt(chi_square / outcomes)"},{"applies_to":["digit_repeat_poisson"],"effect_size_name":"repeat pairs ratio","id":"repeat_pairs_ratio_1_25","reference_or_rationale":"Chuỗi lặp là bình thường trong không gian hữu hạn; chỉ khi số cặp lặp cao hơn kỳ vọng ít nhất 25% mới xem là đủ lớn để theo dõi.","scope":"Tỷ lệ chuỗi kết quả lặp trong không gian hữu hạn.","sensitivity_method":"Đếm lại số phép kiểm đạt ngưỡng khi nhân ngưỡng đã khóa với 0,5; 1,0; 1,5; 2,0.","threshold":1.25,"unit":"observed duplicate pairs / expected duplicate pairs"}],"families":[{"id":"distribution_fit","label":"Khớp phân bố","plain_language":"Đếm xem các số hoặc chữ số có lệch khỏi tần suất kỳ vọng hay không."},{"id":"sequence_dependence","label":"Phụ thuộc theo thời gian","plain_language":"Kiểm tra kết quả gần nhau có tạo thành chuỗi dễ đoán hay không."},{"id":"seasonality","label":"Mùa vụ và lịch","plain_language":"So sánh theo tháng để xem có nhóm thời gian nào lệch rõ hơn phần còn lại."},{"id":"change_point","label":"Điểm đổi chế độ","plain_language":"So nửa đầu với nửa sau để tìm dấu hiệu quy trình thay đổi."},{"id":"co_occurrence","label":"Đồng xuất hiện","plain_language":"Kiểm tra các cặp số hoặc mẫu lặp xuất hiện nhiều hơn mức nền hay không."}],"history_draws":739,"latest_date":"2026-06-13","latest_draw_id":"00739","multiple_testing":{"alpha":0.05,"diagnostic_family_q":"q_value_dependency_family_bh","fallback_decision_q":"q_value_bh before global finalization","method":"benjamini_hochberg","plain_language":"Trạng thái thống kê ưu tiên q toàn hệ thống. q theo họ phụ thuộc chỉ giúp đọc các phép kiểm dùng chung lát dữ liệu hoặc cùng câu hỏi.","primary_decision_q":"q_value_global_bh"},"next_recommended_audit_after_draws":839,"schema_version":1,"scope":"Các kiểm định chỉ dùng dữ liệu công khai đã xác nhận. Kết quả phát hiện bất thường là tín hiệu cần đọc tiếp, không phải bằng chứng gian lận hay kết luận vận hành.","snapshot_id":"789e5dcfdef53f69c758ab10","status_counts":{"pass":7,"practically_large":1,"statistically_notable":1},"strongest_signal":{"algorithm":"Position-wise Chi-Square Test","dependency_family":"digit_frequency_distribution","dependency_family_label":"Tần suất chữ số","effect_size":0.037527,"id":"digit_position_chi_square","interpretation":"Kết quả vượt ngưỡng thống kê sau hiệu chỉnh nhưng chưa đạt ngưỡng độ lớn thực dụng. Mẫu lớn có thể làm sai lệch rất nhỏ trở nên nổi bật.","label":"Tần suất giá trị theo vị trí","p_value":0.00013377,"practical_effect_threshold":0.05,"practically_large":false,"q_value_bh":0.00120393,"q_value_dependency_family_bh":0.00053508,"q_value_global_bh":0.00474883,"statistically_notable":true,"status":"statistically_notable"},"suite_version":"2.0.0","tests":[{"algorithm":"Chi-Square Goodness-of-Fit Test","degrees_of_freedom":9,"dependency_cluster":"digit_marginal_uniformity","dependency_data_view":"digit counts pooled across positions","dependency_family":"digit_frequency_distribution","dependency_family_label":"Tần suất chữ số","dependency_tags":["digit_sequence","digit_counts","pooled_digits"],"effect_size":0.019927,"effect_size_name":"Cohen's w","effect_threshold_id":"cohen_w_0_05","family":"distribution_fit","id":"digit_marginal_chi_square","interpretation":"Chưa vượt ngưỡng thống kê sau hiệu chỉnh và chưa đạt ngưỡng độ lớn thực dụng.","label":"Tần suất giá trị 0 đến 9","p_value":0.0398383,"parameters":{},"plain_language":"Mỗi giá trị hợp lệ nên xuất hiện gần đều trên toàn bộ vị trí quan sát.","practical_effect_threshold":0.05,"practically_large":false,"q_value_bh":0.09123372,"q_value_dependency_family_bh":0.04054832,"q_value_global_bh":0.34837791,"sample_size":14780,"statistic":17.607578,"statistic_name":"chi_square","statistically_notable":false,"status":"pass"},{"algorithm":"G-Test (Likelihood-Ratio Test)","degrees_of_freedom":9,"dependency_cluster":"digit_marginal_uniformity","dependency_data_view":"digit counts pooled across positions","dependency_family":"digit_frequency_distribution","dependency_family_label":"Tần suất chữ số","dependency_tags":["digit_sequence","digit_counts","pooled_digits"],"effect_size":0.019897,"effect_size_name":"likelihood w","effect_threshold_id":"likelihood_w_0_05","family":"distribution_fit","id":"digit_marginal_g_test","interpretation":"Chưa vượt ngưỡng thống kê sau hiệu chỉnh và chưa đạt ngưỡng độ lớn thực dụng.","label":"G-test cho tần suất giá trị","p_value":0.04054832,"parameters":{},"plain_language":"Đo độ lệch giá trị bằng tỷ lệ hợp lý likelihood.","practical_effect_threshold":0.05,"practically_large":false,"q_value_bh":0.09123372,"q_value_dependency_family_bh":0.04054832,"q_value_global_bh":0.34837791,"sample_size":14780,"statistic":17.553166,"statistic_name":"g","statistically_notable":false,"status":"pass"},{"algorithm":"Position-wise Chi-Square Test","degrees_of_freedom":27,"dependency_cluster":"digit_position_uniformity","dependency_data_view":"digit counts split by position","dependency_family":"digit_frequency_distribution","dependency_family_label":"Tần suất chữ số","dependency_tags":["digit_sequence","digit_counts","position_counts"],"effect_size":0.037527,"effect_size_name":"position digit w","effect_threshold_id":"position_digit_w_0_05","family":"distribution_fit","id":"digit_position_chi_square","interpretation":"Kết quả vượt ngưỡng thống kê sau hiệu chỉnh nhưng chưa đạt ngưỡng độ lớn thực dụng. Mẫu lớn có thể làm sai lệch rất nhỏ trở nên nổi bật.","label":"Tần suất giá trị theo vị trí","p_value":0.00013377,"parameters":{"expected_per_position_digit":1478.0,"position_residuals":[{"chi_square_contribution":0.32747,"digit":0,"expected":1478.0,"observed":1500,"position":1,"standardized_residual":0.57225},{"chi_square_contribution":3.315291,"digit":1,"expected":1478.0,"observed":1548,"position":1,"standardized_residual":1.820794},{"chi_square_contribution":0.152233,"digit":2,"expected":1478.0,"observed":1493,"position":1,"standardized_residual":0.39017},{"chi_square_contribution":1.309878,"digit":3,"expected":1478.0,"observed":1522,"position":1,"standardized_residual":1.144499},{"chi_square_contribution":0.782138,"digit":4,"expected":1478.0,"observed":1444,"position":1,"standardized_residual":-0.884386},{"chi_square_contribution":0.152233,"digit":5,"expected":1478.0,"observed":1493,"position":1,"standardized_residual":0.39017},{"chi_square_contribution":0.692828,"digit":6,"expected":1478.0,"observed":1446,"position":1,"standardized_residual":-0.832363},{"chi_square_contribution":0.926252,"digit":7,"expected":1478.0,"observed":1515,"position":1,"standardized_residual":0.96242},{"chi_square_contribution":0.010825,"digit":8,"expected":1478.0,"observed":1474,"position":1,"standardized_residual":-0.104045},{"chi_square_contribution":11.9682,"digit":9,"expected":1478.0,"observed":1345,"position":1,"standardized_residual":-3.459509},{"chi_square_contribution":0.054804,"digit":0,"expected":1478.0,"observed":1469,"position":2,"standardized_residual":-0.234102},{"chi_square_contribution":0.054804,"digit":1,"expected":1478.0,"observed":1487,"position":2,"standardized_residual":0.234102},{"chi_square_contribution":1.494587,"digit":2,"expected":1478.0,"observed":1525,"position":2,"standardized_residual":1.222533},{"chi_square_contribution":0.782138,"digit":3,"expected":1478.0,"observed":1444,"position":2,"standardized_residual":-0.884386},{"chi_square_contribution":2.600812,"digit":4,"expected":1478.0,"observed":1416,"position":2,"standardized_residual":-1.612703},{"chi_square_contribution":5.239513,"digit":5,"expected":1478.0,"observed":1566,"position":2,"standardized_residual":2.288998},{"chi_square_contribution":1.624493,"digit":6,"expected":1478.0,"observed":1527,"position":2,"standardized_residual":1.274556},{"chi_square_contribution":7.317997,"digit":7,"expected":1478.0,"observed":1374,"position":2,"standardized_residual":-2.70518},{"chi_square_contribution":0.298376,"digit":8,"expected":1478.0,"observed":1457,"position":2,"standardized_residual":-0.546238},{"chi_square_contribution":0.926252,"digit":9,"expected":1478.0,"observed":1515,"position":2,"standardized_residual":0.96242},{"chi_square_contribution":0.782138,"digit":0,"expected":1478.0,"observed":1444,"position":3,"standardized_residual":-0.884386},{"chi_square_contribution":0.422869,"digit":1,"expected":1478.0,"observed":1453,"position":3,"standardized_residual":-0.650284},{"chi_square_contribution":0.114344,"digit":2,"expected":1478.0,"observed":1465,"position":3,"standardized_residual":-0.338147},{"chi_square_contribution":0.422869,"digit":3,"expected":1478.0,"observed":1453,"position":3,"standardized_residual":-0.650284},{"chi_square_contribution":0.530447,"digit":4,"expected":1478.0,"observed":1450,"position":3,"standardized_residual":-0.728318},{"chi_square_contribution":0.081867,"digit":5,"expected":1478.0,"observed":1467,"position":3,"standardized_residual":-0.286125},{"chi_square_contribution":17.537889,"digit":6,"expected":1478.0,"observed":1639,"position":3,"standardized_residual":4.187826},{"chi_square_contribution":0.828823,"digit":7,"expected":1478.0,"observed":1443,"position":3,"standardized_residual":-0.910397},{"chi_square_contribution":0.608931,"digit":8,"expected":1478.0,"observed":1448,"position":3,"standardized_residual":-0.78034},{"chi_square_contribution":1.082544,"digit":9,"expected":1478.0,"observed":1518,"position":3,"standardized_residual":1.040454}],"residual_note":"Residual được công bố để giải thích đóng góp vào kiểm định tổng. Không dùng từng ô như một kiểm định độc lập mới."},"plain_language":"Mỗi vị trí của chuỗi nên có các giá trị hợp lệ gần đều nhau.","practical_effect_threshold":0.05,"practically_large":false,"q_value_bh":0.00120393,"q_value_dependency_family_bh":0.00053508,"q_value_global_bh":0.00474883,"sample_size":14780,"statistic":62.443843,"statistic_name":"chi_square","statistically_notable":true,"status":"statistically_notable"},{"algorithm":"Digit-Sum Chi-Square Test","degrees_of_freedom":27,"dependency_cluster":"digit_sum_distribution","dependency_data_view":"digit-sum distribution for each outcome","dependency_family":"digit_sum_structure","dependency_family_label":"Tổng chữ số trong kết quả","dependency_tags":["digit_sequence","digit_sum","within_outcome"],"effect_size":0.03945,"effect_size_name":"digit-sum w","effect_threshold_id":"digit_sum_w_0_10","family":"distribution_fit","id":"digit_sum_distribution","interpretation":"Chưa vượt ngưỡng thống kê sau hiệu chỉnh và chưa đạt ngưỡng độ lớn thực dụng.","label":"Phân bố tổng chữ số","p_value":0.68534011,"parameters":{},"plain_language":"Tổng chữ số có hình dạng kỳ vọng riêng, không phải phân bố đều.","practical_effect_threshold":0.1,"practically_large":false,"q_value_bh":0.77100762,"q_value_dependency_family_bh":0.68534011,"q_value_global_bh":0.83895082,"sample_size":14780,"statistic":23.001737,"statistic_name":"chi_square","statistically_notable":false,"status":"pass"},{"algorithm":"Wald-Wolfowitz Runs Test","degrees_of_freedom":null,"dependency_cluster":"digit_value_order","dependency_data_view":"ordered numeric value of each outcome","dependency_family":"digit_ordered_sequence","dependency_family_label":"Chuỗi kết quả theo thời gian","dependency_tags":["digit_sequence","ordered_draws","numeric_value"],"effect_size":0.005976,"effect_size_name":"absolute z per sqrt(n)","effect_threshold_id":"absolute_z_per_sqrt_n_0_10","family":"sequence_dependence","id":"digit_value_runs","interpretation":"Chưa vượt ngưỡng thống kê sau hiệu chỉnh và chưa đạt ngưỡng độ lớn thực dụng.","label":"Runs test trên giá trị chuỗi","p_value":0.46754446,"parameters":{"center":499.5,"expected_runs":7389.147632,"runs":7345},"plain_language":"Giá trị chuỗi không nên tạo thành nhịp cao thấp quá đều hoặc quá gom cụm.","practical_effect_threshold":0.1,"practically_large":false,"q_value_bh":0.60112859,"q_value_dependency_family_bh":0.46754446,"q_value_global_bh":0.78796413,"sample_size":14780,"statistic":-0.72648,"statistic_name":"z_score","statistically_notable":false,"status":"pass"},{"algorithm":"Lag-1 Autocorrelation Test","degrees_of_freedom":null,"dependency_cluster":"digit_value_order","dependency_data_view":"ordered numeric value of each outcome","dependency_family":"digit_ordered_sequence","dependency_family_label":"Chuỗi kết quả theo thời gian","dependency_tags":["digit_sequence","ordered_draws","numeric_value"],"effect_size":0.006879,"effect_size_name":"absolute correlation","effect_threshold_id":"absolute_correlation_0_05","family":"sequence_dependence","id":"digit_value_lag1_autocorrelation","interpretation":"Chưa vượt ngưỡng thống kê sau hiệu chỉnh và chưa đạt ngưỡng độ lớn thực dụng.","label":"Tự tương quan lag-1 của giá trị chuỗi","p_value":0.40300331,"parameters":{"lag":1},"plain_language":"Kiểm tra chuỗi trước có liên quan tuyến tính với chuỗi ngay sau không.","practical_effect_threshold":0.05,"practically_large":false,"q_value_bh":0.60112859,"q_value_dependency_family_bh":0.46754446,"q_value_global_bh":0.78796413,"sample_size":14779,"statistic":0.006879,"statistic_name":"autocorrelation","statistically_notable":false,"status":"pass"},{"algorithm":"Split-Half Change-Point Test","degrees_of_freedom":null,"dependency_cluster":"digit_sum_change","dependency_data_view":"first-half and second-half digit sums","dependency_family":"digit_ordered_sequence","dependency_family_label":"Chuỗi kết quả theo thời gian","dependency_tags":["digit_sequence","ordered_draws","digit_sum","change_point"],"effect_size":0.024673,"effect_size_name":"standardized mean difference","effect_threshold_id":"standardized_mean_difference_0_15","family":"change_point","id":"digit_sum_split_half_change","interpretation":"Chưa vượt ngưỡng thống kê sau hiệu chỉnh và chưa đạt ngưỡng độ lớn thực dụng.","label":"So nửa đầu và nửa sau bằng tổng chữ số","p_value":0.13366539,"parameters":{"first_half_mean":13.52571,"second_half_mean":13.40406},"plain_language":"Nếu quy trình ổn định, trung bình tổng chữ số giữa hai nửa lịch sử không nên lệch lớn.","practical_effect_threshold":0.15,"practically_large":false,"q_value_bh":0.2405977,"q_value_dependency_family_bh":0.40099617,"q_value_global_bh":0.52928477,"sample_size":14780,"statistic":-1.499803,"statistic_name":"z_score","statistically_notable":false,"status":"pass"},{"algorithm":"Month-by-Digit Chi-Square Test","degrees_of_freedom":99,"dependency_cluster":"digit_calendar_counts","dependency_data_view":"digit counts stratified by calendar month","dependency_family":"digit_frequency_distribution","dependency_family_label":"Tần suất chữ số","dependency_tags":["digit_sequence","digit_counts","calendar_strata"],"effect_size":0.05384,"effect_size_name":"Cramer's style w","effect_threshold_id":"cramers_style_w_0_05","family":"seasonality","id":"digit_month_heterogeneity","interpretation":"Độ lớn đạt ngưỡng thực dụng đã khóa trước nhưng q chưa vượt ngưỡng thống kê. Cần thêm dữ liệu hoặc kiểm tra độ nhạy trước khi diễn giải.","label":"Tần suất giá trị theo tháng","p_value":0.02463647,"parameters":{"months_with_data":12},"plain_language":"So từng tháng với tần suất nền của các giá trị hợp lệ.","practical_effect_threshold":0.05,"practically_large":true,"q_value_bh":0.09123372,"q_value_dependency_family_bh":0.04054832,"q_value_global_bh":0.34837791,"sample_size":14780,"statistic":128.52956,"statistic_name":"chi_square","statistically_notable":false,"status":"practically_large"},{"algorithm":"Poisson Repeat-Rate Test","degrees_of_freedom":null,"dependency_cluster":"digit_duplicate_pairs","dependency_data_view":"duplicate outcome pairs across the confirmed history","dependency_family":"digit_repeat_structure","dependency_family_label":"Lặp chuỗi kết quả","dependency_tags":["digit_sequence","outcome_identity","repeat_pairs"],"effect_size":0.999791,"effect_size_name":"repeat pairs ratio","effect_threshold_id":"repeat_pairs_ratio_1_25","family":"co_occurrence","id":"digit_repeat_poisson","interpretation":"Chưa vượt ngưỡng thống kê sau hiệu chỉnh và chưa đạt ngưỡng độ lớn thực dụng.","label":"Tỷ lệ chuỗi lặp lại","p_value":0.94497299,"parameters":{"expected_duplicate_pairs":109216.81,"observed_duplicate_pairs":109194,"outcome_space":1000},"plain_language":"Trong không gian hữu hạn, chuỗi lặp là bình thường, nhưng tỷ lệ lặp quá cao cần xem lại.","practical_effect_threshold":1.25,"practically_large":false,"q_value_bh":0.94497299,"q_value_dependency_family_bh":0.94497299,"q_value_global_bh":0.98666297,"sample_size":14780,"statistic":-0.069021,"statistic_name":"z_score","statistically_notable":false,"status":"pass"}],"title":"Bộ kiểm định công bằng thống kê"},"backtest":{"audit_comparison":{"approximate_p_value":0.35064864,"beats_baseline":false,"beats_baseline_unadjusted":false,"confidence_interval_lower":-0.021951,"confidence_interval_upper":0.061863,"confidence_level":0.95,"mean_position_match_difference":0.019956,"multiple_testing_method":"benjamini_hochberg","multiple_testing_scope":24,"paired_z_score":0.933332,"q_value_global_bh":0.64735134,"standard_error":0.021382},"audit_model":{"average_best_position_matches":1.471049,"exact_hit_rate":0.021909,"exact_hits":14,"strategy":"audit_signal"},"audit_score_policy":"audit=0.45*long_hot+0.35*recent+0.20*short","baseline":{"average_best_position_matches":1.451092,"candidate_space_size":1000,"expected_exact_hit_rate":0.019818,"expected_exact_hits":12.664,"method":"exact_sequence_enumeration","score_distribution":[{"average_probability":0.001882629108,"expected_count":1.203,"matches":0},{"average_probability":0.564960876369,"expected_count":361.01,"matches":1},{"average_probability":0.413338028169,"expected_count":264.123,"matches":2},{"average_probability":0.019818466354,"expected_count":12.664,"matches":3}],"strategy":"uniform_exact_expectation"},"comparison":{"approximate_p_value":0.98587477,"beats_baseline":false,"beats_baseline_unadjusted":false,"confidence_interval_lower":-0.043354,"confidence_interval_upper":0.042577,"confidence_level":0.95,"mean_position_match_difference":-0.000388,"multiple_testing_method":"benjamini_hochberg","multiple_testing_scope":24,"paired_z_score":-0.017704,"q_value_global_bh":0.98587477,"standard_error":0.021922},"first_test_draw_id":"00101","initial_training_draws":100,"latest_test_draw_id":"00739","method":"walk_forward","minimum_history_draws":100,"model":{"average_best_position_matches":1.450704,"exact_hit_rate":0.028169,"exact_hits":18,"strategy":"balanced_signal"},"recent_comparison":{"approximate_p_value":0.54244994,"beats_baseline":false,"beats_baseline_unadjusted":false,"confidence_interval_lower":-0.054441,"confidence_interval_upper":0.028626,"confidence_level":0.95,"mean_position_match_difference":-0.012908,"multiple_testing_method":"benjamini_hochberg","multiple_testing_scope":24,"paired_z_score":-0.609112,"q_value_global_bh":0.78353886,"standard_error":0.021191},"recent_model":{"average_best_position_matches":1.438185,"exact_hit_rate":0.020344,"exact_hits":13,"strategy":"recent_frequency"},"recent_window_draws":500,"samples":639,"schema_version":2,"score_policy":"recent=0.6*short+0.4*recent; balanced=0.4*short+0.3*recent-0.2*long","short_window_draws":50,"status":"complete","symbol_max":9,"symbol_min":0,"warning":"Baseline được tính chính xác trên toàn bộ không gian chuỗi hợp lệ của từng kỳ. Các kết quả cùng một kỳ ở trò chơi nhiều hạng giải không hoàn toàn độc lập, vì vậy p-value vẫn chỉ là xấp xỉ và cần được đọc cùng kích thước hiệu ứng."},"data_quality":{"candidate_gaps":{"classification_counts":{},"count":0,"interpretation":"An absent numeric ID is a candidate gap only. It is not classified as a missing draw without source evidence.","ranges":[]},"checks":{"file_order_regressions":0,"invalid_json_rows":0,"missing_required_fields":{},"validation_mismatches":0},"draw_confirmation":{"confirmed":739},"first_date":"2021-09-14","last_date":"2026-06-13","max_id":"00739","min_id":"00001","prize_coverage":{"draws_with_prize_rows":739,"prize_rows":5912,"rate":1.0},"prize_status":{"complete":739},"result_coverage":{"rate":1.0,"rows_with_result":739},"rows":739,"source_agreement":{"conflict_count_reason":"Raw source observations were not retained consistently in legacy rows.","conflicts":null,"multi_source_consensus":0,"official_direct":0,"official_verified_match":739,"pending_official":0,"single_secondary_source":0,"unknown":0},"source_origin":{"official":739},"source_verification":{"official_verified_match":739},"structural_validity":{"valid":739}},"product":{"active":true,"kind":"digit_sequence","name":"Max 3D Pro","note":"Báo cáo mô tả toàn bộ bộ ba số được công bố ở các hạng giải.","short_name":"3D Pro","slug":"max3dpro"},"schema_version":1,"summary":{"average_draws_per_active_day":1.0,"calendar_days_with_draws":739,"confirmed_draws":739,"data_quality":{"canonical_rows":739,"cross_checked_rate":1.0,"cross_checked_rows":739,"official_source_rate":1.0,"official_source_rows":739,"prize_coverage_draws":739,"prize_coverage_rate":1.0,"result_coverage_rate":1.0,"result_coverage_rows":739,"source_origins":{"official":739},"source_verification":{"official_verified_match":739}},"data_sources":{"official_vietlott":739},"draws_by_month":[{"draws":64,"month":1},{"draws":58,"month":2},{"draws":66,"month":3},{"draws":65,"month":4},{"draws":66,"month":5},{"draws":57,"month":6},{"draws":53,"month":7},{"draws":54,"month":8},{"draws":59,"month":9},{"draws":66,"month":10},{"draws":65,"month":11},{"draws":66,"month":12}],"draws_by_weekday":[{"draws":0,"weekday":0},{"draws":245,"weekday":1},{"draws":0,"weekday":2},{"draws":248,"weekday":3},{"draws":0,"weekday":4},{"draws":246,"weekday":5},{"draws":0,"weekday":6}],"first_date":"2021-09-14","first_draw_id":"00001","largest_jackpot":null,"latest_date":"2026-06-13","latest_draw_id":"00739","latest_jackpot":null,"not_confirmed_draws":0,"prizes":{"draws_with_prizes":739,"estimated_payout_vnd":564619560000,"largest_prize_draw_id":"00001","largest_prize_value_vnd":2000000000,"reported_winners":3928843,"rows":5912},"recent_draws":[{"draw_date":"2026-06-13","draw_id":"00739","result":{"outcomes":["283","920","609","721","072","112","568","418","907","134","615","771","436","941","768","051","598","502","862","382"]}},{"draw_date":"2026-06-11","draw_id":"00738","result":{"outcomes":["365","615","279","858","412","970","250","295","053","420","781","873","167","440","022","541","868","621","917","570"]}},{"draw_date":"2026-06-09","draw_id":"00737","result":{"outcomes":["111","544","437","080","315","020","894","423","485","428","945","360","888","788","062","163","425","549","876","959"]}},{"draw_date":"2026-06-06","draw_id":"00736","result":{"outcomes":["724","505","117","410","951","628","328","588","017","948","614","072","376","157","215","689","803","491","228","391"]}},{"draw_date":"2026-06-04","draw_id":"00735","result":{"outcomes":["811","110","833","374","124","300","407","572","377","562","681","166","182","316","825","099","973","374","137","910"]}},{"draw_date":"2026-06-02","draw_id":"00734","result":{"outcomes":["255","563","245","142","184","200","577","695","267","366","984","223","313","015","001","373","791","118","856","360"]}},{"draw_date":"2026-05-30","draw_id":"00733","result":{"outcomes":["428","512","878","991","618","999","399","376","922","364","417","572","276","611","076","474","530","201","817","370"]}},{"draw_date":"2026-05-28","draw_id":"00732","result":{"outcomes":["250","917","350","559","684","599","268","552","467","770","785","839","508","637","446","367","638","716","127","226"]}},{"draw_date":"2026-05-26","draw_id":"00731","result":{"outcomes":["554","570","633","623","763","981","500","095","583","268","249","782","357","577","739","163","737","061","284","786"]}},{"draw_date":"2026-05-23","draw_id":"00730","result":{"outcomes":["197","270","202","259","393","340","800","098","816","410","048","895","040","543","004","823","876","046","189","249"]}},{"draw_date":"2026-05-21","draw_id":"00729","result":{"outcomes":["125","420","068","392","264","779","608","125","295","582","535","053","825","472","326","511","798","804","408","794"]}},{"draw_date":"2026-05-19","draw_id":"00728","result":{"outcomes":["803","005","927","093","357","081","228","816","252","732","167","016","368","659","480","764","688","350","885","843"]}}],"source_hosts":{"vietlott.vn":739},"validation_statuses":{"valid":739}},"weather":{"associations":[{"correlation":0.0,"label":"Nhiệt độ trung bình","p_value":1.0,"q_value_bh":1.0,"sample_days":0,"status":"descriptive","variable":"temperature"},{"correlation":0.0,"label":"Độ ẩm trung bình","p_value":1.0,"q_value_bh":1.0,"sample_days":0,"status":"descriptive","variable":"humidity"}],"conclusion":"Chưa đủ ngày có cả kết quả quay và dữ liệu thời tiết để kiểm tra.","coverage":{"coverage_rate":0.0,"first_date":null,"latest_date":null,"matched_days":0,"matched_draws":0,"total_draws":739,"venues":[]},"limitations":["Đây là thời tiết ngoài trời tái phân tích, không phải cảm biến trong phòng quay.","Dữ liệu theo ngày không biết nhiệt độ đúng phút quay hoặc hoạt động điều hòa.","Không có mã máy, mã bộ bi, bảo trì và luồng khí để suy luận cơ chế."],"method":"Mỗi ngày chỉ tạo một điểm dữ liệu. Tương quan được tính sau khi trừ trung bình trong cùng tháng-năm và địa điểm; p được hoán vị trong các khối đó, q hiệu chỉnh hai phép kiểm.","outcome_feature":{"label":"Tổng chữ số trung bình trong ngày","unit":"điểm mô tả"},"schema_version":1,"source":{"documentation":"https://open-meteo.com/en/docs/historical-weather-api","model":"ERA5-Land","name":"Open-Meteo Historical Weather API","venue_source":"https://www.vietlott.vn/vi/tin-tuc/20199-thong-bao-thay-doi-dia-diem-trung-tam-quay-so-mo-thuong/"},"status":"missing","temperature_bands":[]}}
